SikuliLibrary/__init__.py
SikuliLibrary/keywords.py
SikuliLibrary/sikuli.py
SikuliLibrary/version.py
SikuliLibrary/lib/SikuliLibrary.jar
robotframework_sikulilibrary-2.0.5.dist-info/licenses/LICENSE.txt
robotframework_sikulilibrary-2.0.5.dist-info/METADATA
robotframework_sikulilibrary-2.0.5.dist-info/WHEEL
robotframework_sikulilibrary-2.0.5.dist-info/top_level.txt
robotframework_sikulilibrary-2.0.5.dist-info/RECORD
