Metadata-Version: 2.4
Name: robotframework-SikuliLibrary
Version: 2.0.5
Summary: Sikuli Robot Framework Library provide keywords for Robot Framework to test UI through Sikuli.
Home-page: https://github.com/MarketSquare/robotframework-SikuliLibrary
Author: Wang Yang
Author-email: wang_yang1980@hotmail.com
Maintainer: Hélio Guilherme
Maintainer-email: helioxentric@gmail.com
License: Apache-2.0
Keywords: robotframework testing testautomation sikuli UI
Platform: any
Classifier: Development Status :: 5 - Production/Stable
Classifier: Operating System :: OS Independent
Classifier: Programming Language :: Java
Classifier: Programming Language :: Python :: 3
Classifier: Topic :: Software Development :: Testing
Classifier: Framework :: Robot Framework
Classifier: Framework :: Robot Framework :: Library
Requires-Python: >=3.8,<4.0
License-File: LICENSE.txt
Dynamic: author
Dynamic: author-email
Dynamic: classifier
Dynamic: description
Dynamic: description-content-type
Dynamic: home-page
Dynamic: keywords
Dynamic: license
Dynamic: license-file
Dynamic: maintainer
Dynamic: maintainer-email
Dynamic: platform
Dynamic: requires-python
Dynamic: summary
